main.py
thinftp/__init__.py
thinftp/errors.py
thinftp/fileman.py
thinftp/handler.py
thinftp/logger.py
thinftp/server.py
thinftp-0.1.1.dist-info/licenses/LICENSE
thinftp-0.1.1.dist-info/METADATA
thinftp-0.1.1.dist-info/WHEEL
thinftp-0.1.1.dist-info/entry_points.txt
thinftp-0.1.1.dist-info/top_level.txt
thinftp-0.1.1.dist-info/RECORD
