Metadata-Version: 2.4
Name: thinftp
Version: 0.1.1
Summary: A very minimal FTP server
Author-email: "M.V.Harish Kumar" <harishtpj@gmail.com>
License-Expression: MIT
Project-URL: Documentation, https://thinftp.readthedocs.io
Project-URL: Repository, https://github.com/harishtpj/thinftp
Requires-Python: >=3.11
License-File: LICENSE
Provides-Extra: docs
Requires-Dist: sphinx>=7.0; extra == "docs"
Requires-Dist: pydata-sphinx-theme; extra == "docs"
Requires-Dist: sphinx-autodoc-typehints; extra == "docs"
Requires-Dist: myst-parser; extra == "docs"
Dynamic: license-file
